psilon/__about__.py
psilon/__init__.py
psilon-0.0.1.dist-info/METADATA
psilon-0.0.1.dist-info/WHEEL
psilon-0.0.1.dist-info/licenses/LICENSE.txt
psilon-0.0.1.dist-info/RECORD
